<vra xmlns="http://www.vraweb.org/vracore4.htm" xmlns:xsi="http://www.w3.org/2001/XMLSchema-instance" xsi:schemaLocation="http://www.vraweb.org/vracore4.htm http://cluster-schemas.uni-hd.de/vra-strictCluster.xsd">
	<work id="w_039cbfea-a770-5eaa-b65c-9b47dd04b591" source="EXC Priya Paul Collection" refid="c_b9827ec8-6b66-5d98-9f5e-ca12b58044c4">
		<agentSet>
		</agentSet>
		<culturalContextSet>
			<culturalContext/>
		</culturalContextSet>
		<dateSet>
		</dateSet>
		<descriptionSet>
			<description source=" " lang="en" script="latn">This textile label shows a number of animals. In the center of the image a hyena, a zebra, an antelope, an ox and a lion are standing next to each other. In the corners and sides of the image, swans and other birds are depicted.</description>
		</descriptionSet>
		<inscriptionSet>
			<inscription>
				<author/>
				<position/>
				<text type="text" lang="en">Nathumal Shorimal
Amritsar Sole Importers
Sundar B.</text>
			</inscription>
		</inscriptionSet>
		<locationSet>
			<location type="repository">
				<name type="corporate" vocab="local" refid="4d99a9b1-9f01-556a-80ae-e5ff7789e46f">Delhi / The Priya Paul Collection of Popular Art"</name>
				<refid/>
			</location>
			<location source="EXC" type="repository">
				<name type="geographic" vocab="" refid="">511###Delhi / The Priya Paul Collection of Popular Art</name>
			</location>
		</locationSet>
		<materialSet>

			<material vocab="LOCAL" refid="ce497196-b1b5-52ee-9f08-bb6627e56ef2" type="medium">paper (fiber product)</material>
		</materialSet>
		<measurementsSet>
		</measurementsSet>
		<relationSet>
			<relation type="imageIs" relids="i_4d99a9b1-9f01-556a-80ae-e5ff7789e46f" refid="108852" source="EXC Priya Paul Collection">Overall view</relation>
		</relationSet>
		<rightsSet>
			<rights type="copyrighted">
				<rightsHolder/>
				<text>Copyrighted. Copyright with the original artists and publishers.</text>
			</rights>
		</rightsSet>
		<sourceSet>
			<source>
				<name type=""/>
				<refid type=""/>
			</source>
		</sourceSet>
		<stateEditionSet>
			<notes/>
			<stateEdition/>
		</stateEditionSet>
		<stylePeriodSet>
		</stylePeriodSet>
		<subjectSet>
<!-- ToDo: RefIDs für alle -->
			<subject source="EXC" vocab="LOCAL" refid="">
				<term>textile label</term>
			</subject>
			<subject source="EXC" vocab="LOCAL" refid="">
				<term>recheck</term>
			</subject>
			<subject source="EXC" vocab="LOCAL" refid="">
				<term>recheck-Matthias</term>
			</subject>
			<subject source="EXC" vocab="LOCAL" refid="">
				<term>swan</term>
			</subject>
			<subject source="EXC" vocab="LOCAL" refid="">
				<term>zebra</term>
			</subject>
			<subject source="EXC" vocab="LOCAL" refid="">
				<term>recheck-Medialab</term>
			</subject>
			<subject source="EXC" vocab="LOCAL" refid="">
				<term>Kaloo Mall Shori Mall</term>
			</subject>
			<subject source="EXC" vocab="LOCAL" refid="">
				<term>hyena</term>
			</subject>
			<subject source="EXC" vocab="LOCAL" refid="">
				<term>recheck-Gerhard</term>
			</subject>
			<subject source="EXC" vocab="LOCAL" refid="">
				<term>antelope</term>
			</subject>
			<subject source="EXC" vocab="LOCAL" refid="">
				<term>ox</term>
			</subject>
			<subject source="EXC" vocab="LOCAL" refid="">
				<term>lion</term>
			</subject>
		</subjectSet>
		<textrefSet>
			<textref>
				<name/>
				<refid source=""/>
			</textref>
		</textrefSet>
		<techniqueSet>
			<technique vocab="LOCAL" refid="05e81717-b5c1-552f-bafc-950a0f1ad2df">chromolithographs</technique>
		</techniqueSet>
		<titleSet>
			<title type="descriptive" pref="true" lang="en" script="latn">Textile label by Nathumal Shorimal, Amritsar, Sundar B.</title>
		</titleSet>
		<worktypeSet>
			<worktype vocab="" refid="">textile label</worktype>
		</worktypeSet>
		<hra:heidicon>
			<hra:item type="f_id_heidicon" status="0" display="Heidicon image_id">
				<hra:value>http://heidicon.ub.uni-heidelberg.de/id/108852</hra:value>
				<hra:value>108852</hra:value>
			</hra:item>
		</hra:heidicon>
		<hra:heidicon>
			<hra:administrative type="heidicon2vra" date="2012-09-04 16:10:49">
			</hra:administrative>
		</hra:heidicon>
	</work>
</vra>