<vra xmlns="http://www.vraweb.org/vracore4.htm" xmlns:xsi="http://www.w3.org/2001/XMLSchema-instance" xsi:schemaLocation="http://www.vraweb.org/vracore4.htm http://cluster-schemas.uni-hd.de/vra-strictCluster.xsd">
	<work id="w_0d1414db-0073-5012-afce-efac3655604b" source="EXC Priya Paul Collection" refid="c_b9827ec8-6b66-5d98-9f5e-ca12b58044c4">
		<agentSet>
		</agentSet>
		<culturalContextSet>
			<culturalContext/>
		</culturalContextSet>
		<dateSet>
			<date type="creation">
				<earliestDate>1973</earliestDate>
				<latestDate>1973</latestDate>
			</date>
		</dateSet>
		<descriptionSet>
			<description source=" " lang="en" script="latn">A lobby card for the movie "Junoon" released in 1978 shows the male protagonist, Shashi Kapoor on a horse looking toward two women sitting in a tonga (the horse cart) while the tonga driver looks at Shashi Kapoor. Another man stands besides the horse. The tonga has an umbrella to provide shade. The actors wear typical Muslim clothes of 19th Century.</description>
		</descriptionSet>
		<inscriptionSet>
			<inscription>
				<author/>
				<position/>
				<text type="text" lang="en">Shashi Kapoor presents 
Junoon
a film by Shyam Benegal</text>
			</inscription>
		</inscriptionSet>
		<locationSet>
			<location type="repository">
				<name type="corporate" vocab="local" refid="a6c30491-20b2-54da-b03f-e9d2147bc03b">Delhi / The Priya Paul Collection of Popular Art"</name>
				<refid/>
			</location>
			<location source="EXC" type="repository">
				<name type="geographic" vocab="" refid="">511###Delhi / The Priya Paul Collection of Popular Art</name>
			</location>
		</locationSet>
		<materialSet>

			<material vocab="LOCAL" refid="3bb2d971-9842-5ae4-9df0-14afecf70bb1" type="medium">photographic paper</material>
		</materialSet>
		<measurementsSet>
		</measurementsSet>
		<relationSet>
			<relation type="imageIs" relids="i_a6c30491-20b2-54da-b03f-e9d2147bc03b" refid="120863" source="EXC Priya Paul Collection">Overall view</relation>
		</relationSet>
		<rightsSet>
			<rights type="copyrighted">
				<rightsHolder/>
				<text>Copyrighted. Copyright with the original artists and publishers.</text>
			</rights>
		</rightsSet>
		<sourceSet>
			<source>
				<name type=""/>
				<refid type=""/>
			</source>
		</sourceSet>
		<stateEditionSet>
			<notes/>
			<stateEdition/>
		</stateEditionSet>
		<stylePeriodSet>
		</stylePeriodSet>
		<subjectSet>
<!-- ToDo: RefIDs für alle -->
			<subject source="EXC" vocab="LOCAL" refid="">
				<term>recheck</term>
			</subject>
			<subject source="EXC" vocab="LOCAL" refid="">
				<term>Shyam Benegal</term>
			</subject>
			<subject source="EXC" vocab="LOCAL" refid="">
				<term>Bollywood</term>
			</subject>
			<subject source="EXC" vocab="LOCAL" refid="">
				<term>tonga</term>
			</subject>
			<subject source="EXC" vocab="LOCAL" refid="">
				<term>Jalal Agha</term>
			</subject>
			<subject source="EXC" vocab="LOCAL" refid="">
				<term>recheck-Gerhard</term>
			</subject>
			<subject source="EXC" vocab="LOCAL" refid="">
				<term>truck</term>
			</subject>
			<subject source="EXC" vocab="LOCAL" refid="">
				<term>Nafisa Ali</term>
			</subject>
			<subject source="EXC" vocab="LOCAL" refid="">
				<term>Hindi Film</term>
			</subject>
			<subject source="EXC" vocab="LOCAL" refid="">
				<term>lobby card</term>
			</subject>
			<subject source="EXC" vocab="LOCAL" refid="">
				<term>Shashi Kapoor</term>
			</subject>
			<subject source="EXC" vocab="LOCAL" refid="">
				<term>Tom Alter</term>
			</subject>
			<subject source="EXC" vocab="LOCAL" refid="">
				<term>horse</term>
			</subject>
			<subject source="EXC" vocab="LOCAL" refid="">
				<term>turban</term>
			</subject>
		</subjectSet>
		<textrefSet>
			<textref>
				<name/>
				<refid source=""/>
			</textref>
		</textrefSet>
		<techniqueSet>
			<technique vocab="LOCAL" refid="6688815e-8d89-55fb-91ca-14c288014a8c">color prints (photographs)</technique>
		</techniqueSet>
		<titleSet>
			<title type="descriptive" pref="true" lang="en" script="latn">"Junoon"</title>
		</titleSet>
		<worktypeSet>
			<worktype vocab="" refid="">lobby cards</worktype>
		</worktypeSet>
		<hra:heidicon>
			<hra:item type="t_rh" status="0" display="comment:related_hyperlinks">
				<hra:value>http://www.imdb.com/title/tt0077783/</hra:value>
				<hra:value>2011-12-14</hra:value>
				<hra:value>story line, leading actors, director.</hra:value>
				<hra:value>6</hra:value>
			</hra:item>
		</hra:heidicon>
		<hra:heidicon>
			<hra:item type="f_id_heidicon" status="0" display="Heidicon image_id">
				<hra:value>http://heidicon.ub.uni-heidelberg.de/id/120863</hra:value>
				<hra:value>120863</hra:value>
			</hra:item>
		</hra:heidicon>
		<hra:heidicon>
			<hra:administrative type="heidicon2vra" date="2012-09-04 16:11:07">
			</hra:administrative>
		</hra:heidicon>
	</work>
</vra>