<vra    xmlns="http://www.vraweb.org/vracore4.htm"
        xmlns:xsi="http://www.w3.org/2001/XMLSchema-instance"
        xmlns:hra="http://cluster-schemas.uni-hd.de"
        xsi:schemaLocation="http://www.vraweb.org/vracore4.htm http://cluster-schemas.uni-hd.de/vra-strictCluster.xsd">

	<work id="w_0ee91f44-5bc2-569e-ab65-3552d7ec1f2b" source="EXC Priya Paul Collection" refid="c_b9827ec8-6b66-5d98-9f5e-ca12b58044c4">
		<agentSet>
		</agentSet>
		<culturalContextSet>
			<culturalContext/>
		</culturalContextSet>
		<dateSet>
		</dateSet>
		<descriptionSet>
		</descriptionSet>
		<inscriptionSet>
		</inscriptionSet>
		<locationSet>
			<location type="repository">
				<name type="corporate" vocab="local" refid="8523b821-3c7b-53c9-8151-214ad6747722">Delhi / The Priya Paul Collection of Popular Art"</name>
				<refid/>
			</location>
			<location source="EXC" type="repository">
				<name type="geographic" vocab="" refid="">511###Delhi / The Priya Paul Collection of Popular Art</name>
			</location>
		</locationSet>
		<materialSet>

			<material vocab="LOCAL" refid="ce497196-b1b5-52ee-9f08-bb6627e56ef2" type="medium">paper (fiber product)</material>
		</materialSet>
		<measurementsSet>
			<notes>12 cm x 12 cm, circular</notes>
			<measurements type="height" unit="cm">12</measurements>
			<measurements type="width" unit="cm">12</measurements>
			<measurements type="shape"> circular</measurements>
		</measurementsSet>
		<relationSet>
			<relation type="imageIs" relids="i_8523b821-3c7b-53c9-8151-214ad6747722" refid="120577" source="EXC Priya Paul Collection">Overall view</relation>
		</relationSet>
		<rightsSet>
			<rights type="copyrighted">
				<rightsHolder/>
				<text>Copyrighted. Copyright with the original artists and publishers.</text>
			</rights>
		</rightsSet>
		<sourceSet>
			<source>
				<name type=""/>
				<refid type=""/>
			</source>
		</sourceSet>
		<stateEditionSet>
			<notes/>
			<stateEdition/>
		</stateEditionSet>
		<stylePeriodSet>
		</stylePeriodSet>
		<subjectSet>
<!-- ToDo: RefIDs für alle -->
		</subjectSet>
		<textrefSet>
			<textref>
				<name/>
				<refid source=""/>
			</textref>
		</textrefSet>
		<techniqueSet>
			<technique vocab="LOCAL" refid="05e81717-b5c1-552f-bafc-950a0f1ad2df">chromolithographs</technique>
		</techniqueSet>
		<titleSet>
			<title type="descriptive" pref="true" lang="en" script="latn">Textile label showing a deity riding an elephant</title>
		</titleSet>
		<worktypeSet>
			<worktype vocab="" refid="">textile label</worktype>
		</worktypeSet>
		<hra:heidicon>
			<hra:item type="f_zusammenhang" status="0" display="zusammenhang">
				<hra:value>good</hra:value>
			</hra:item>
		</hra:heidicon>
		<hra:heidicon>
			<hra:item type="f_id_heidicon" status="0" display="Heidicon image_id">
				<hra:value>http://heidicon.ub.uni-heidelberg.de/id/120577</hra:value>
				<hra:value>120577</hra:value>
			</hra:item>
		</hra:heidicon>
		<hra:heidicon>
			<hra:administrative type="heidicon2vra" date="2012-09-04 15:57:44">
			</hra:administrative>
		</hra:heidicon>
	</work>
</vra>