<vra    xmlns="http://www.vraweb.org/vracore4.htm"
        xmlns:xsi="http://www.w3.org/2001/XMLSchema-instance"
        xmlns:hra="http://cluster-schemas.uni-hd.de"
        xsi:schemaLocation="http://www.vraweb.org/vracore4.htm http://cluster-schemas.uni-hd.de/vra-strictCluster.xsd">

	<work id="w_43115a95-c2a8-5d56-b451-925d0bc7011e" source="EXC Priya Paul Collection" refid="c_b9827ec8-6b66-5d98-9f5e-ca12b58044c4">
		<agentSet>
			<agent>
				<culture/>
				<name vocab="local" type="personal" refid="uuid-ba7fa408-a6cf-589b-8765-ad477a2e2a31">Vishnu</name>
				<role/>
  			</agent>
			<agent>
				<culture/>
				<name vocab="local" type="personal" refid="uuid-b48d1160-e490-5472-8f4d-938355ab4cea">Kali</name>
				<role/>
  			</agent>
			<agent>
				<culture/>
				<name vocab="local" type="personal" refid="uuid-dfc58ea6-295f-5f25-a46b-84c54142bbb8">Sharma, S. N.</name>
				<role/>
  			</agent>
		</agentSet>
		<culturalContextSet>
			<culturalContext/>
		</culturalContextSet>
		<dateSet>
		</dateSet>
		<descriptionSet>
			<description vocab="" refid="" lang="en" script="latn">surface-mounted</description>
		</descriptionSet>
		<inscriptionSet>
			<inscription>
				<author/>
				<position/>
				<text type="text" lang="en">S. N. Sharma</text>
			</inscription>
			<inscription>
				<author/>
				<position/>
				<text type="signature">S. N. Sharma</text>
			</inscription>
		</inscriptionSet>
		<locationSet>
			<location type="repository">
				<name type="corporate" vocab="local" refid="8181e9d6-203b-5d5b-afaf-d906cd75db56">Delhi / The Priya Paul Collection of Popular Art"</name>
				<refid/>
			</location>
			<location source="EXC" type="repository">
				<name type="geographic" vocab="" refid="">511###Delhi / The Priya Paul Collection of Popular Art</name>
			</location>
		</locationSet>
		<materialSet>

			<material vocab="LOCAL" refid="1c7d6eac-19d4-5d62-b1b1-2210092b5bad" type="medium">panels (wood)</material>
			<material vocab="LOCAL" refid="ce497196-b1b5-52ee-9f08-bb6627e56ef2" type="medium">paper (fiber product)</material>
		</materialSet>
		<measurementsSet>
		</measurementsSet>
		<relationSet>
			<relation type="imageIs" relids="i_8181e9d6-203b-5d5b-afaf-d906cd75db56" refid="118835" source="EXC Priya Paul Collection">Overall view</relation>
		</relationSet>
		<rightsSet>
			<rights type="copyrighted">
				<rightsHolder/>
				<text>Copyrighted. Copyright with the original artists and publishers.</text>
			</rights>
		</rightsSet>
		<sourceSet>
			<source>
				<name type=""/>
				<refid type=""/>
			</source>
		</sourceSet>
		<stateEditionSet>
			<notes/>
			<stateEdition/>
		</stateEditionSet>
		<stylePeriodSet>
		</stylePeriodSet>
		<subjectSet>
<!-- ToDo: RefIDs für alle -->
			<subject source="EXC" vocab="LOCAL" refid="dfc58ea6-295f-5f25-a46b-84c54142bbb8">
				<term>Sharma, S. N.</term>
			</subject>
			<subject source="EXC" vocab="LOCAL" refid="b48d1160-e490-5472-8f4d-938355ab4cea">
				<term>Kali</term>
			</subject>
			<subject source="EXC" vocab="LOCAL" refid="ba7fa408-a6cf-589b-8765-ad477a2e2a31">
				<term>Vishnu</term>
			</subject>
		</subjectSet>
		<textrefSet>
			<textref>
				<name/>
				<refid source=""/>
			</textref>
		</textrefSet>
		<techniqueSet>
			<technique vocab="LOCAL" refid="94acfcac-0bbf-5bc1-bbaf-887d8a7ad873">paintings (visual works)</technique>
		</techniqueSet>
		<titleSet>
			<title type="descriptive" pref="true" lang="en" script="latn">Kali and Vishnu, Hindu deities</title>
		</titleSet>
		<worktypeSet>
			<worktype vocab="" refid="">paintings (visual works)</worktype>
			<worktype vocab="" refid="">calendars</worktype>
		</worktypeSet>
		<hra:heidicon>
			<hra:item type="f_autor_zeichen" status="0" display="Artist (characters)">
				<hra:value>Sharma, S. N.</hra:value>
			</hra:item>
		</hra:heidicon>
		<hra:heidicon>
			<hra:item type="f_id_heidicon" status="0" display="Heidicon image_id">
				<hra:value>http://heidicon.ub.uni-heidelberg.de/id/118835</hra:value>
				<hra:value>118835</hra:value>
			</hra:item>
		</hra:heidicon>
		<hra:heidicon>
			<hra:administrative type="heidicon2vra" date="2012-09-04 16:03:30">
			</hra:administrative>
		</hra:heidicon>
	</work>
</vra>