<vra    xmlns="http://www.vraweb.org/vracore4.htm"
        xmlns:xsi="http://www.w3.org/2001/XMLSchema-instance"
        xmlns:hra="http://cluster-schemas.uni-hd.de"
        xsi:schemaLocation="http://www.vraweb.org/vracore4.htm http://cluster-schemas.uni-hd.de/vra-strictCluster.xsd">

	<work id="w_4d682a96-b521-574e-b516-1629ff4a12a4" source="EXC Priya Paul Collection" refid="c_b9827ec8-6b66-5d98-9f5e-ca12b58044c4">
		<agentSet>
			<agent>
				<culture/>
				<name vocab="local" type="personal" refid="uuid-664f87db-93fc-53c2-bcc1-94d6a30fe186">Krishna</name>
				<role/>
  			</agent>
		</agentSet>
		<culturalContextSet>
			<culturalContext/>
		</culturalContextSet>
		<dateSet>
			<date type="creation">
				<earliestDate>1956</earliestDate>
				<latestDate>1956</latestDate>
			</date>
		</dateSet>
		<descriptionSet>
			<description source=" " lang="en" script="latn">A color-tinted movie poster from the 1956 released Hindi film, Dwarikadheesh shows Lord Krishna's alliance with Rukmini (played by the actress Nirupama Roy). Lord Krishna wears a garland and looks toward Rukmini. Narad Muni is seen on extreme left with Veena (Indian classical music instrument) hanging across his shoulders. He wears a garland and blesses the couple. Lord Krishna's elder brother, Balram stands behind Lord Krishna and Rukmini with his hand placed on top confirming alliance of Lord Krishna and Rukmini. 

It looks like the film scene is set in a Lord Shiva temple or in Lord Krishna's palace (behind one can see Lord Shiva's Trishul). The film actors are dressed up in colourful traditional Indian attire. All men, except narad muni are wearing bejewelled crowns and jewellery while the women wear flowers in their hair.</description>
		</descriptionSet>
		<inscriptionSet>
			<inscription>
				<author/>
				<position/>
				<text type="text" lang="en">Bhagyodaya Pictures 
Directed by Natwarshyam
Dwarikadheesh
[...] not readable due to aging</text>
			</inscription>
			<inscription>
				<author/>
				<position/>
				<text type="text" lang="hi">PLEASE ENTER HERE</text>
			</inscription>
		</inscriptionSet>
		<locationSet>
			<location type="repository">
				<name type="corporate" vocab="local" refid="9223cfc9-780e-5db2-80e6-8dc3a3b1ad59">Delhi / The Priya Paul Collection of Popular Art"</name>
				<refid/>
			</location>
			<location source="EXC" type="repository">
				<name type="geographic" vocab="" refid="">511###Delhi / The Priya Paul Collection of Popular Art</name>
			</location>
		</locationSet>
		<materialSet>

			<material vocab="LOCAL" refid="3bb2d971-9842-5ae4-9df0-14afecf70bb1" type="medium">photographic paper</material>
		</materialSet>
		<measurementsSet>
		</measurementsSet>
		<relationSet>
			<relation type="imageIs" relids="i_9223cfc9-780e-5db2-80e6-8dc3a3b1ad59" refid="120851" source="EXC Priya Paul Collection">Overall view</relation>
		</relationSet>
		<rightsSet>
			<rights type="copyrighted">
				<rightsHolder/>
				<text>Copyrighted. Copyright with the original artists and publishers.</text>
			</rights>
		</rightsSet>
		<sourceSet>
			<source>
				<name type=""/>
				<refid type=""/>
			</source>
		</sourceSet>
		<stateEditionSet>
			<notes/>
			<stateEdition/>
		</stateEditionSet>
		<stylePeriodSet>
		</stylePeriodSet>
		<subjectSet>
<!-- ToDo: RefIDs für alle -->
			<subject source="EXC" vocab="LOCAL" refid="">
				<term>Durga Khote</term>
			</subject>
			<subject source="EXC" vocab="LOCAL" refid="">
				<term>Natwarshyam</term>
			</subject>
			<subject source="EXC" vocab="LOCAL" refid="">
				<term>jewellery</term>
			</subject>
			<subject source="EXC" vocab="LOCAL" refid="">
				<term>musical instrument</term>
			</subject>
			<subject source="EXC" vocab="LOCAL" refid="">
				<term>recheck</term>
			</subject>
			<subject source="EXC" vocab="LOCAL" refid="">
				<term>lobby card</term>
			</subject>
			<subject source="EXC" vocab="LOCAL" refid="">
				<term>Sulochana</term>
			</subject>
			<subject source="EXC" vocab="LOCAL" refid="">
				<term>Dwarikadheesh</term>
			</subject>
			<subject source="EXC" vocab="LOCAL" refid="">
				<term>flower</term>
			</subject>
			<subject source="EXC" vocab="LOCAL" refid="">
				<term>recheck-Gerhard</term>
			</subject>
			<subject source="EXC" vocab="LOCAL" refid="">
				<term>sari</term>
			</subject>
			<subject source="EXC" vocab="LOCAL" refid="">
				<term>Hindi Film</term>
			</subject>
			<subject source="EXC" vocab="LOCAL" refid="">
				<term>Bollywood</term>
			</subject>
			<subject source="EXC" vocab="LOCAL" refid="">
				<term>Hinduism</term>
			</subject>
			<subject source="EXC" vocab="LOCAL" refid="664f87db-93fc-53c2-bcc1-94d6a30fe186">
				<term>Krishna</term>
			</subject>
			<subject source="EXC" vocab="LOCAL" refid="">
				<term>musician</term>
			</subject>
		</subjectSet>
		<textrefSet>
			<textref>
				<name/>
				<refid source=""/>
			</textref>
		</textrefSet>
		<techniqueSet>
			<technique vocab="LOCAL" refid="6688815e-8d89-55fb-91ca-14c288014a8c">color prints (photographs)</technique>
		</techniqueSet>
		<titleSet>
			<title type="descriptive" pref="true" lang="en" script="latn">"Dwarikadheesh"</title>
		</titleSet>
		<worktypeSet>
			<worktype vocab="" refid="">lobby cards</worktype>
		</worktypeSet>
		<hra:heidicon>
			<hra:item type="t_rh" status="0" display="comment:related_hyperlinks">
				<hra:value>http://www.jointscene.com/movies/bollywood/Dwarikadheesh/15612#casts</hra:value>
				<hra:value>2011-12-13</hra:value>
				<hra:value>Indian Cinema Online Register</hra:value>
				<hra:value>6</hra:value>
			</hra:item>
		</hra:heidicon>
		<hra:heidicon>
			<hra:item type="f_id_heidicon" status="0" display="Heidicon image_id">
				<hra:value>http://heidicon.ub.uni-heidelberg.de/id/120851</hra:value>
				<hra:value>120851</hra:value>
			</hra:item>
		</hra:heidicon>
		<hra:heidicon>
			<hra:administrative type="heidicon2vra" date="2012-09-04 16:09:47">
			</hra:administrative>
		</hra:heidicon>
	</work>
</vra>