<vra xmlns="http://www.vraweb.org/vracore4.htm" xmlns:xsi="http://www.w3.org/2001/XMLSchema-instance" xsi:schemaLocation="http://www.vraweb.org/vracore4.htm http://cluster-schemas.uni-hd.de/vra-strictCluster.xsd">
	<work id="w_576959de-0fc0-5c6c-9f3c-4c960975eb7c" source="EXC Priya Paul Collection" refid="c_b9827ec8-6b66-5d98-9f5e-ca12b58044c4">
		<agentSet>
		</agentSet>
		<culturalContextSet>
			<culturalContext/>
		</culturalContextSet>
		<dateSet>
		</dateSet>
		<descriptionSet>
			<description source=" " lang="en" script="latn">The center of the image shows the portrait of an Indian woman in an advertisement for Noor-e-Gulshan hair oil. The painted portrait is surrounded by four symmetrically arranged flowers as part of the overall graphic design. The top and lower parts of the image are reserved for the text of the advertisement.</description>
		</descriptionSet>
		<inscriptionSet>
			<inscription>
				<author/>
				<position/>
				<text type="text" lang="en">HAIR OIL</text>
			</inscription>
			<inscription>
				<author/>
				<position/>
				<text type="text" lang="hi">नूरे गुलशन</text>
			</inscription>
			<inscription>
				<author/>
				<position/>
				<text type="text" lang="hi">कैमीकल उद्योगशाला
हाथरस</text>
			</inscription>
		</inscriptionSet>
		<locationSet>
			<location type="repository">
				<name type="corporate" vocab="local" refid="7ccf033c-7912-56bd-a10e-53db4aaef917">Delhi / The Priya Paul Collection of Popular Art"</name>
				<refid/>
			</location>
			<location source="EXC" type="repository">
				<name type="geographic" vocab="" refid="">511###Delhi / The Priya Paul Collection of Popular Art</name>
			</location>
		</locationSet>
		<materialSet>

			<material vocab="LOCAL" refid="ce497196-b1b5-52ee-9f08-bb6627e56ef2" type="medium">paper (fiber product)</material>
		</materialSet>
		<measurementsSet>
			<notes>10 cm x 5 cm, portrait</notes>
			<measurements type="height" unit="cm">10</measurements>
			<measurements type="width" unit="cm">5</measurements>
			<measurements type="shape"> portrait</measurements>
		</measurementsSet>
		<relationSet>
			<relation type="imageIs" relids="i_7ccf033c-7912-56bd-a10e-53db4aaef917" refid="120552" source="EXC Priya Paul Collection">Overall view</relation>
		</relationSet>
		<rightsSet>
			<rights type="copyrighted">
				<rightsHolder/>
				<text>Copyrighted. Copyright with the original artists and publishers.</text>
			</rights>
		</rightsSet>
		<sourceSet>
			<source>
				<name type=""/>
				<refid type=""/>
			</source>
		</sourceSet>
		<stateEditionSet>
			<notes/>
			<stateEdition/>
		</stateEditionSet>
		<stylePeriodSet>
		</stylePeriodSet>
		<subjectSet>
<!-- ToDo: RefIDs für alle -->
			<subject source="EXC" vocab="LOCAL" refid="">
				<term>Noor-e-Gulshan Hair Oil</term>
			</subject>
			<subject source="EXC" vocab="LOCAL" refid="">
				<term>hair oil</term>
			</subject>
			<subject source="EXC" vocab="LOCAL" refid="">
				<term>recheck</term>
			</subject>
			<subject source="EXC" vocab="LOCAL" refid="">
				<term>advertisement</term>
			</subject>
			<subject source="EXC" vocab="LOCAL" refid="">
				<term>product advertisement</term>
			</subject>
			<subject source="EXC" vocab="LOCAL" refid="">
				<term>recheck-jo</term>
			</subject>
			<subject source="EXC" vocab="LOCAL" refid="">
				<term>recheck-original-language</term>
			</subject>
			<subject source="EXC" vocab="LOCAL" refid="">
				<term>Indian woman</term>
			</subject>
			<subject source="SWD" vocab="" refid="">
				<term>Blume &amp;lt;Motiv&amp;gt;</term>
			</subject>
			<subject source="SWD" vocab="" refid="">
				<term>Inderin</term>
			</subject>
			<subject source="SWD" vocab="" refid="">
				<term>Anzeigenwerbung</term>
			</subject>
			<subject source="SWD" vocab="" refid="">
				<term>Werbung</term>
			</subject>
			<subject source="SWD" vocab="" refid="">
				<term>Frau &amp;lt;20-40 Jahre&amp;gt;</term>
			</subject>
			<subject source="SWD" vocab="" refid="">
				<term>Haar &amp;lt;Motiv&amp;gt;</term>
			</subject>
		</subjectSet>
		<textrefSet>
			<textref>
				<name/>
				<refid source=""/>
			</textref>
		</textrefSet>
		<techniqueSet>
			<technique vocab="LOCAL" refid="05e81717-b5c1-552f-bafc-950a0f1ad2df">chromolithographs</technique>
		</techniqueSet>
		<titleSet>
			<title type="descriptive" pref="true" lang="en" script="latn">Noor-e Gulshan Hair Oil Advertisement</title>
			<title type="descriptive" pref="false" lang="" script="">नूरे गुलशन</title>
		</titleSet>
		<worktypeSet>
			<worktype vocab="" refid="">advertisements</worktype>
		</worktypeSet>
		<hra:heidicon>
			<hra:item type="f_zusammenhang" status="0" display="zusammenhang">
				<hra:value>good</hra:value>
			</hra:item>
		</hra:heidicon>
		<hra:heidicon>
			<hra:item type="f_id_heidicon" status="0" display="Heidicon image_id">
				<hra:value>http://heidicon.ub.uni-heidelberg.de/id/120552</hra:value>
				<hra:value>120552</hra:value>
			</hra:item>
		</hra:heidicon>
		<hra:heidicon>
			<hra:administrative type="heidicon2vra" date="2012-09-04 15:56:41">
			</hra:administrative>
		</hra:heidicon>
	</work>
</vra>