<vra xmlns="http://www.vraweb.org/vracore4.htm" xmlns:xsi="http://www.w3.org/2001/XMLSchema-instance" xsi:schemaLocation="http://www.vraweb.org/vracore4.htm http://cluster-schemas.uni-hd.de/vra-strictCluster.xsd">
	<work id="w_577805fe-9ec2-5f7a-af44-f277ea86a8b5" source="EXC Priya Paul Collection" refid="c_b9827ec8-6b66-5d98-9f5e-ca12b58044c4">
		<agentSet>
		</agentSet>
		<culturalContextSet>
			<culturalContext/>
		</culturalContextSet>
		<dateSet>
		</dateSet>
		<descriptionSet>
			<description source=" " lang="en" script="latn">This textile label of the United Merchants Company Ltd. shows a musician playing a sitar. He is wearing a topi and is sitting on a carpet with a tiger pattern.</description>
		</descriptionSet>
		<inscriptionSet>
			<inscription>
				<author/>
				<position/>
				<text type="text" lang="en">The United Merchants Co. Ltd.</text>
			</inscription>
			<inscription>
				<author/>
				<position/>
				<text type="text" lang="en">Trade Mark</text>
			</inscription>
			<inscription>
				<author/>
				<position/>
				<text type="text" lang="en">Bombay</text>
			</inscription>
			<inscription>
				<author/>
				<position/>
				<text type="text" lang="??">ADD TEXT HERE</text>
			</inscription>
		</inscriptionSet>
		<locationSet>
			<location type="repository">
				<name type="corporate" vocab="local" refid="9e19472d-b1b5-5ca5-98dc-525fc0d0474a">Delhi / The Priya Paul Collection of Popular Art"</name>
				<refid/>
			</location>
			<location source="EXC" type="repository">
				<name type="geographic" vocab="" refid="">511###Delhi / The Priya Paul Collection of Popular Art</name>
			</location>
		</locationSet>
		<materialSet>

			<material vocab="LOCAL" refid="ce497196-b1b5-52ee-9f08-bb6627e56ef2" type="medium">paper (fiber product)</material>
		</materialSet>
		<measurementsSet>
			<notes>H 15 cm, W 10 cm, portrait</notes>
			<measurements type="height" unit="cm">15</measurements>
			<measurements type="width" unit="cm">10</measurements>
			<measurements type="shape"> portrait</measurements>
		</measurementsSet>
		<relationSet>
			<relation type="imageIs" relids="i_9e19472d-b1b5-5ca5-98dc-525fc0d0474a" refid="120058" source="EXC Priya Paul Collection">Overall view</relation>
		</relationSet>
		<rightsSet>
			<rights type="copyrighted">
				<rightsHolder/>
				<text>Copyrighted. Copyright with the original artists and publishers.</text>
			</rights>
		</rightsSet>
		<sourceSet>
			<source>
				<name type=""/>
				<refid type=""/>
			</source>
		</sourceSet>
		<stateEditionSet>
			<notes/>
			<stateEdition/>
		</stateEditionSet>
		<stylePeriodSet>
		</stylePeriodSet>
		<subjectSet>
<!-- ToDo: RefIDs für alle -->
			<subject source="EXC" vocab="LOCAL" refid="">
				<term>carpet</term>
			</subject>
			<subject source="EXC" vocab="LOCAL" refid="">
				<term>sitar</term>
			</subject>
			<subject source="EXC" vocab="LOCAL" refid="">
				<term>recheck-Medialab</term>
			</subject>
			<subject source="EXC" vocab="LOCAL" refid="">
				<term>decoration</term>
			</subject>
			<subject source="EXC" vocab="LOCAL" refid="">
				<term>flower</term>
			</subject>
			<subject source="EXC" vocab="LOCAL" refid="">
				<term>recheck-Matthias</term>
			</subject>
			<subject source="EXC" vocab="LOCAL" refid="">
				<term>recheck</term>
			</subject>
			<subject source="EXC" vocab="LOCAL" refid="">
				<term>recheck-Gerhard</term>
			</subject>
			<subject source="EXC" vocab="LOCAL" refid="">
				<term>topi</term>
			</subject>
			<subject source="EXC" vocab="LOCAL" refid="">
				<term>musical instrument</term>
			</subject>
			<subject source="EXC" vocab="LOCAL" refid="">
				<term>United Merchants Company Ltd.</term>
			</subject>
			<subject source="EXC" vocab="LOCAL" refid="">
				<term>floral pattern</term>
			</subject>
			<subject source="EXC" vocab="LOCAL" refid="">
				<term>fantastic script</term>
			</subject>
			<subject source="EXC" vocab="LOCAL" refid="">
				<term>musician</term>
			</subject>
		</subjectSet>
		<textrefSet>
			<textref>
				<name/>
				<refid source=""/>
			</textref>
		</textrefSet>
		<techniqueSet>
			<technique vocab="LOCAL" refid="05e81717-b5c1-552f-bafc-950a0f1ad2df">chromolithographs</technique>
		</techniqueSet>
		<titleSet>
			<title type="descriptive" pref="true" lang="en" script="latn">Textile label of The United Merchants Co. Ltd.</title>
		</titleSet>
		<worktypeSet>
			<worktype vocab="" refid="">textile label</worktype>
		</worktypeSet>
		<hra:heidicon>
			<hra:item type="f_zusammenhang" status="0" display="zusammenhang">
				<hra:value>good</hra:value>
			</hra:item>
		</hra:heidicon>
		<hra:heidicon>
			<hra:item type="f_id_heidicon" status="0" display="Heidicon image_id">
				<hra:value>http://heidicon.ub.uni-heidelberg.de/id/120058</hra:value>
				<hra:value>120058</hra:value>
			</hra:item>
		</hra:heidicon>
		<hra:heidicon>
			<hra:administrative type="heidicon2vra" date="2012-09-04 16:10:09">
			</hra:administrative>
		</hra:heidicon>
	</work>
</vra>