<vra    xmlns="http://www.vraweb.org/vracore4.htm"
        xmlns:xsi="http://www.w3.org/2001/XMLSchema-instance"
        xmlns:hra="http://cluster-schemas.uni-hd.de"
        xsi:schemaLocation="http://www.vraweb.org/vracore4.htm http://cluster-schemas.uni-hd.de/vra-strictCluster.xsd">

	<work id="w_a0e12745-248f-5950-8608-0829eea3d7dc" source="EXC Priya Paul Collection" refid="c_b9827ec8-6b66-5d98-9f5e-ca12b58044c4">
		<agentSet>
			<agent>
				<culture/>
				<name vocab="local" type="personal" refid="uuid-f16038a5-7630-5bb9-8d9e-a3d5f7faa3a2">Sita</name>
				<role/>
  			</agent>
			<agent>
				<culture/>
				<name vocab="local" type="personal" refid="uuid-048694c0-93ed-5b54-8923-fb9017e4b9ae">Rama</name>
				<role/>
  			</agent>
			<agent>
				<culture/>
				<name vocab="local" type="personal" refid="uuid-ec2e7db2-15f9-5a22-a8fb-c86471f48a9d">Ravana</name>
				<role/>
  			</agent>
			<agent>
				<culture/>
				<name vocab="local" type="personal" refid="uuid-92738bf8-9745-52a0-a3ed-b5be424fc86a">Sharma, M. L.</name>
				<role/>
  			</agent>
			<agent>
				<culture/>
				<name vocab="local" type="corporate" refid="uuid-e56887bc-fb57-5307-b9d3-42a6d4cb78d2">Empire Calendar Manufacturing Co.</name>
				<role/>
  			</agent>
		</agentSet>
		<culturalContextSet>
			<culturalContext/>
		</culturalContextSet>
		<dateSet>
		</dateSet>
		<descriptionSet>
		</descriptionSet>
		<inscriptionSet>
		</inscriptionSet>
		<locationSet>
			<location type="repository">
				<name type="corporate" vocab="local" refid="74cdf224-e766-510f-a748-e0699937149c">Delhi / The Priya Paul Collection of Popular Art"</name>
				<refid/>
			</location>
			<location source="EXC" type="repository">
				<name type="geographic" vocab="" refid="">511###Delhi / The Priya Paul Collection of Popular Art</name>
			</location>
		</locationSet>
		<materialSet>

			<material vocab="LOCAL" refid="ce497196-b1b5-52ee-9f08-bb6627e56ef2" type="medium">paper (fiber product)</material>
		</materialSet>
		<measurementsSet>
			<notes>25 cm x 17 cm, portrait</notes>
			<measurements type="height" unit="cm">25</measurements>
			<measurements type="width" unit="cm">17</measurements>
			<measurements type="shape"> portrait</measurements>
		</measurementsSet>
		<relationSet>
			<relation type="imageIs" relids="i_74cdf224-e766-510f-a748-e0699937149c" refid="119964" source="EXC Priya Paul Collection">Overall view</relation>
		</relationSet>
		<rightsSet>
			<rights type="copyrighted">
				<rightsHolder/>
				<text>Copyrighted. Copyright with the original artists and publishers.</text>
			</rights>
		</rightsSet>
		<sourceSet>
			<source>
				<name type=""/>
				<refid type=""/>
			</source>
		</sourceSet>
		<stateEditionSet>
			<notes/>
			<stateEdition/>
		</stateEditionSet>
		<stylePeriodSet>
		</stylePeriodSet>
		<subjectSet>
<!-- ToDo: RefIDs für alle -->
		</subjectSet>
		<textrefSet>
			<textref>
				<name/>
				<refid source=""/>
			</textref>
		</textrefSet>
		<techniqueSet>
			<technique vocab="LOCAL" refid="05e81717-b5c1-552f-bafc-950a0f1ad2df">chromolithographs</technique>
		</techniqueSet>
		<titleSet>
			<title type="descriptive" pref="true" lang="en" script="latn">Portrait of a lady (in blue sari- interior of a house)</title>
		</titleSet>
		<worktypeSet>
			<worktype vocab="" refid="">posters</worktype>
		</worktypeSet>
		<hra:heidicon>
			<hra:item type="f_zusammenhang" status="0" display="zusammenhang">
				<hra:value>good</hra:value>
			</hra:item>
		</hra:heidicon>
		<hra:heidicon>
			<hra:item type="f_id_heidicon" status="0" display="Heidicon image_id">
				<hra:value>http://heidicon.ub.uni-heidelberg.de/id/119964</hra:value>
				<hra:value>119964</hra:value>
			</hra:item>
		</hra:heidicon>
		<hra:heidicon>
			<hra:administrative type="heidicon2vra" date="2012-09-04 16:07:11">
			</hra:administrative>
		</hra:heidicon>
	</work>
</vra>