<vra xmlns="http://www.vraweb.org/vracore4.htm" xmlns:xsi="http://www.w3.org/2001/XMLSchema-instance" xsi:schemaLocation="http://www.vraweb.org/vracore4.htm http://cluster-schemas.uni-hd.de/vra-strictCluster.xsd">
	<work id="w_a4c34316-0d4d-52f5-9205-7ad8f15b1699" source="EXC Priya Paul Collection" refid="c_b9827ec8-6b66-5d98-9f5e-ca12b58044c4">
		<agentSet>
			<agent>
				<culture/>
				<name vocab="local" type="personal" refid="uuid-048694c0-93ed-5b54-8923-fb9017e4b9ae">Rama</name>
				<role/>
  			</agent>
			<agent>
				<culture/>
				<name vocab="local" type="personal" refid="uuid-ec2e7db2-15f9-5a22-a8fb-c86471f48a9d">Ravana</name>
				<role/>
  			</agent>
			<agent>
				<culture/>
				<name vocab="local" type="corporate" refid="uuid-d2945550-c20d-50cd-897a-7d5f93208a2b">Alexander Drew & Sons</name>
				<role/>
  			</agent>
		</agentSet>
		<culturalContextSet>
			<culturalContext/>
		</culturalContextSet>
		<dateSet>
		</dateSet>
		<descriptionSet>
			<description source=" " lang="en" script="latn">On this textile label from Alexander Drew &amp; Sons, a battlefield scene can be seen. Rama on the right, on a chariot, is seen battling Ravan on the left with his multiple heads. Rama's army comprises of monkeys, who sent his troops out to fight the demons of  Ravan on the upper right side. The armies fight each other with bows and arrows, swords and lances.</description>
		</descriptionSet>
		<inscriptionSet>
			<inscription>
				<author/>
				<position/>
				<text type="text" lang="en">Alexander Drew &amp; Sons.
Ram Chand Seal &amp; Co.</text>
			</inscription>
			<inscription>
				<author/>
				<position/>
				<text type="text" lang="en">Mahabharata
Series No.25</text>
			</inscription>
			<inscription>
				<author/>
				<position/>
				<text type="text" lang="en">Rec. No.
57884</text>
			</inscription>
			<inscription>
				<author/>
				<position/>
				<text type="text" lang="hi">राम चान्द सील एन्ड काः</text>
			</inscription>
			<inscription>
				<author/>
				<position/>
				<text type="text" lang="bn"></text>
			</inscription>
		</inscriptionSet>
		<locationSet>
			<location type="repository">
				<name type="corporate" vocab="local" refid="b514e06d-7df0-5d4e-8478-69229328cd7b">Delhi / The Priya Paul Collection of Popular Art"</name>
				<refid/>
			</location>
			<location source="EXC" type="repository">
				<name type="geographic" vocab="" refid="">511###Delhi / The Priya Paul Collection of Popular Art</name>
			</location>
		</locationSet>
		<materialSet>

			<material vocab="LOCAL" refid="ce497196-b1b5-52ee-9f08-bb6627e56ef2" type="medium">paper (fiber product)</material>
		</materialSet>
		<measurementsSet>
			<notes>H 12 cm, W 10 cm, portrait</notes>
			<measurements type="height" unit="cm">12</measurements>
			<measurements type="width" unit="cm">10</measurements>
			<measurements type="shape"> portrait</measurements>
		</measurementsSet>
		<relationSet>
			<relation type="imageIs" relids="i_b514e06d-7df0-5d4e-8478-69229328cd7b" refid="120093" source="EXC Priya Paul Collection">Overall view</relation>
		</relationSet>
		<rightsSet>
			<rights type="copyrighted">
				<rightsHolder/>
				<text>Copyrighted. Copyright with the original artists and publishers.</text>
			</rights>
		</rightsSet>
		<sourceSet>
			<source>
				<name type=""/>
				<refid type=""/>
			</source>
		</sourceSet>
		<stateEditionSet>
			<notes/>
			<stateEdition/>
		</stateEditionSet>
		<stylePeriodSet>
		</stylePeriodSet>
		<subjectSet>
<!-- ToDo: RefIDs für alle -->
			<subject source="EXC" vocab="LOCAL" refid="">
				<term>chariot</term>
			</subject>
			<subject source="EXC" vocab="LOCAL" refid="">
				<term>monkey</term>
			</subject>
			<subject source="EXC" vocab="LOCAL" refid="">
				<term>recheck</term>
			</subject>
			<subject source="EXC" vocab="LOCAL" refid="">
				<term>Devanagari-Script</term>
			</subject>
			<subject source="EXC" vocab="LOCAL" refid="">
				<term>recheck-Medialab</term>
			</subject>
			<subject source="EXC" vocab="LOCAL" refid="048694c0-93ed-5b54-8923-fb9017e4b9ae">
				<term>Rama</term>
			</subject>
			<subject source="EXC" vocab="LOCAL" refid="">
				<term>bow</term>
			</subject>
			<subject source="EXC" vocab="LOCAL" refid="">
				<term>script</term>
			</subject>
			<subject source="EXC" vocab="LOCAL" refid="">
				<term>recheck-original-language</term>
			</subject>
			<subject source="EXC" vocab="LOCAL" refid="">
				<term>battle</term>
			</subject>
			<subject source="EXC" vocab="LOCAL" refid="ec2e7db2-15f9-5a22-a8fb-c86471f48a9d">
				<term>Ravana</term>
			</subject>
			<subject source="EXC" vocab="LOCAL" refid="">
				<term>horse</term>
			</subject>
			<subject source="EXC" vocab="LOCAL" refid="d2945550-c20d-50cd-897a-7d5f93208a2b">
				<term>Alexander Drew &amp;amp; Sons</term>
			</subject>
			<subject source="EXC" vocab="LOCAL" refid="">
				<term>Ramayana</term>
			</subject>
			<subject source="EXC" vocab="LOCAL" refid="">
				<term>arrow</term>
			</subject>
			<subject source="SWD" vocab="" refid="">
				<term>Werbung</term>
			</subject>
		</subjectSet>
		<textrefSet>
			<textref>
				<name/>
				<refid source=""/>
			</textref>
		</textrefSet>
		<techniqueSet>
			<technique vocab="LOCAL" refid="05e81717-b5c1-552f-bafc-950a0f1ad2df">chromolithographs</technique>
		</techniqueSet>
		<titleSet>
			<title type="descriptive" pref="true" lang="en" script="latn">Textile label by Alexander Drew &amp; Sons</title>
		</titleSet>
		<worktypeSet>
			<worktype vocab="" refid="">textile label</worktype>
		</worktypeSet>
		<hra:heidicon>
			<hra:item type="t_rl" status="0" display="comment:related_literature">
				<hra:value>Freitag, Sandria B. 2002. “The realm of the visual: Agency and modern civil society.” in: Contributions to Indian Sociology. 36 (1 &amp; 2). pp.: 365-397.</hra:value>
			</hra:item>
			<hra:item type="t_rl" status="0" display="comment:related_literature">
				<hra:value>Masselos, Jim 2006. “A goddess for everyone: the mass production of divine images,” in Jackie Menzies, ed. Goddess Divine Energy. Sydney: Art Gallery of New South Wales and Thames and Hudson.</hra:value>
			</hra:item>
			<hra:item type="t_rl" status="0" display="comment:related_literature">
				<hra:value>Rajagopal, Arvind 2010. "The Commodity Image in the (Post) Colony" http://www.tasveergharindia.net/cmsdesk/essay/100/index_1.html fig.9 (17.1.2011)</hra:value>
			</hra:item>
		</hra:heidicon>
		<hra:heidicon>
			<hra:item type="f_zusammenhang" status="0" display="zusammenhang">
				<hra:value>good</hra:value>
			</hra:item>
		</hra:heidicon>
		<hra:heidicon>
			<hra:item type="f_id_heidicon" status="0" display="Heidicon image_id">
				<hra:value>http://heidicon.ub.uni-heidelberg.de/id/120093</hra:value>
				<hra:value>120093</hra:value>
			</hra:item>
		</hra:heidicon>
		<hra:heidicon>
			<hra:administrative type="heidicon2vra" date="2012-09-04 15:55:53">
			</hra:administrative>
		</hra:heidicon>
	</work>
</vra>