<vra xmlns="http://www.vraweb.org/vracore4.htm" xmlns:xsi="http://www.w3.org/2001/XMLSchema-instance" xsi:schemaLocation="http://www.vraweb.org/vracore4.htm http://cluster-schemas.uni-hd.de/vra-strictCluster.xsd">
	<work id="w_c966435d-90d3-5422-bea3-e78e75c7846d" source="EXC Priya Paul Collection" refid="c_b9827ec8-6b66-5d98-9f5e-ca12b58044c4">
		<agentSet>
			<agent>
				<culture/>
				<name vocab="local" type="personal" refid="uuid-c6cb8cfe-8adf-5536-827c-f106cd10d735">Osman Ali</name>
				<role/>
  			</agent>
		</agentSet>
		<culturalContextSet>
			<culturalContext/>
		</culturalContextSet>
		<dateSet>
			<date type="creation">
				<earliestDate>1940</earliestDate>
				<latestDate>1940</latestDate>
			</date>
		</dateSet>
		<descriptionSet>
		</descriptionSet>
		<inscriptionSet>
			<inscription>
				<author/>
				<position/>
				<text type="text" lang="fa">نوید مسیح</text>
			</inscription>
			<inscription>
				<author/>
				<position/>
				<text type="other" lang="fa">"Navid-e Masih", the promised arrival of the Messiah</text>
			</inscription>
			<inscription>
				<author/>
				<position/>
				<text type="text" lang="en">English version of the Christmas Persian Poem composed by His Exalted Highness The Nizam Of Hyderabad and translated by
Sir Nizamat Jung, Ex-Member of Council</text>
			</inscription>
		</inscriptionSet>
		<locationSet>
			<location type="repository">
				<name type="corporate" vocab="local" refid="b71597c6-1193-5611-a470-13769bacee6c">Delhi / The Priya Paul Collection of Popular Art"</name>
				<refid/>
			</location>
			<location source="EXC" type="repository">
				<name type="geographic" vocab="" refid="">511###Delhi / The Priya Paul Collection of Popular Art</name>
			</location>
		</locationSet>
		<materialSet>

			<material vocab="LOCAL" refid="ce497196-b1b5-52ee-9f08-bb6627e56ef2" type="medium">paper (fiber product)</material>
		</materialSet>
		<measurementsSet>
			<notes>H 30 cm, W 20 cm, portrait</notes>
			<measurements type="height" unit="cm">30</measurements>
			<measurements type="width" unit="cm">20</measurements>
			<measurements type="shape"> portrait</measurements>
		</measurementsSet>
		<relationSet>
			<relation type="imageIs" relids="i_b71597c6-1193-5611-a470-13769bacee6c" refid="119791" source="EXC Priya Paul Collection">Overall view</relation>
		</relationSet>
		<rightsSet>
			<rights type="copyrighted">
				<rightsHolder/>
				<text>Copyrighted. Copyright with the original artists and publishers.</text>
			</rights>
		</rightsSet>
		<sourceSet>
			<source>
				<name type=""/>
				<refid type=""/>
			</source>
		</sourceSet>
		<stateEditionSet>
			<notes/>
			<stateEdition/>
		</stateEditionSet>
		<stylePeriodSet>
			<stylePeriod vocab="" refid="">1940s</stylePeriod>
		</stylePeriodSet>
		<subjectSet>
<!-- ToDo: RefIDs für alle -->
			<subject source="EXC" vocab="LOCAL" refid="">
				<term>Persian (language)</term>
			</subject>
			<subject source="EXC" vocab="LOCAL" refid="">
				<term>Eid Mubarak</term>
			</subject>
			<subject source="EXC" vocab="LOCAL" refid="c6cb8cfe-8adf-5536-827c-f106cd10d735">
				<term>Osman Ali</term>
			</subject>
			<subject source="EXC" vocab="LOCAL" refid="">
				<term>recheck</term>
			</subject>
			<subject source="EXC" vocab="LOCAL" refid="">
				<term>recheck-Medialab</term>
			</subject>
			<subject source="EXC" vocab="LOCAL" refid="">
				<term>Times of India Yearbook</term>
			</subject>
			<subject source="EXC" vocab="LOCAL" refid="">
				<term>greeting cards</term>
			</subject>
			<subject source="EXC" vocab="LOCAL" refid="">
				<term>recheck-original-language</term>
			</subject>
			<subject source="EXC" vocab="LOCAL" refid="">
				<term>Nizam of Hyderabad</term>
			</subject>
			<subject source="EXC" vocab="LOCAL" refid="">
				<term>Times of India</term>
			</subject>
			<subject source="SWD" vocab="" refid="">
				<term>Jahrbuch</term>
			</subject>
		</subjectSet>
		<textrefSet>
			<textref>
				<name/>
				<refid source=""/>
			</textref>
		</textrefSet>
		<techniqueSet>
			<technique vocab="LOCAL" refid="9f5fddf6-ee5f-5aa5-8d7a-a13ad68b41b8">prints (visual works)</technique>
		</techniqueSet>
		<titleSet>
			<title type="descriptive" pref="true" lang="en" script="latn">Christmas Persian Poem composed by the Nizam of Hyderabad</title>
			<title type="descriptive" pref="false" lang="" script="">"Navid-e Masih", the promised arrival of the Messiah</title>
			<title type="descriptive" pref="false" lang="" script="">نوید مسیح</title>
		</titleSet>
		<worktypeSet>
			<worktype vocab="" refid="">pages</worktype>
		</worktypeSet>
		<hra:heidicon>
			<hra:item type="t_rl" status="0" display="comment:related_literature">
				<hra:value>Patterson, Steven, Postcards from the Raj, Patterns of Prejudice, Volume 40, Number 2, Routledge, May 2006, 142-158; also see Saloni Mathur, 1999.</hra:value>
			</hra:item>
			<hra:item type="t_rl" status="0" display="comment:related_literature">
				<hra:value>Mathur, Saloni, "Wanted Native Views: Collecting colonial postcards of India," in Antionette Burton (ed.) Gender, Sexuality and Colonial Modernities, New York: Routledge, 1999, 95-115.</hra:value>
			</hra:item>
		</hra:heidicon>
		<hra:heidicon>
			<hra:item type="t_rh" status="0" display="comment:related_hyperlinks">
				<hra:value>http://www.tasveergharindia.net/cmsdesk/essay/117/index_1.html</hra:value>
				<hra:value>2011-04-04</hra:value>
				<hra:value></hra:value>
				<hra:value>6</hra:value>
			</hra:item>
		</hra:heidicon>
		<hra:heidicon>
			<hra:item type="f_zusammenhang" status="0" display="zusammenhang">
				<hra:value>good</hra:value>
			</hra:item>
		</hra:heidicon>
		<hra:heidicon>
			<hra:item type="f_id_heidicon" status="0" display="Heidicon image_id">
				<hra:value>http://heidicon.ub.uni-heidelberg.de/id/119791</hra:value>
				<hra:value>119791</hra:value>
			</hra:item>
		</hra:heidicon>
		<hra:heidicon>
			<hra:administrative type="heidicon2vra" date="2012-09-04 16:01:14">
			</hra:administrative>
		</hra:heidicon>
	</work>
</vra>